varphi_devkit/__init__.py
varphi_devkit/compiler.py
varphi_devkit/exceptions.py
varphi_devkit/parser/Varphi.interp
varphi_devkit/parser/Varphi.tokens
varphi_devkit/parser/VarphiLexer.interp
varphi_devkit/parser/VarphiLexer.py
varphi_devkit/parser/VarphiLexer.tokens
varphi_devkit/parser/VarphiListener.py
varphi_devkit/parser/VarphiParser.py
varphi_devkit/parser/__init__.py
varphi_devkit-2.0.6.dist-info/WHEEL
varphi_devkit-2.0.6.dist-info/METADATA
varphi_devkit-2.0.6.dist-info/RECORD
