Metadata-Version: 2.3
Name: varphi-devkit
Version: 2.0.6
Summary: A framework for building compilers, interpreters, and analysis tools for the Varphi language.
Author: Varphi
Author-email: Varphi <support@varphi-lang.com>
Requires-Dist: antlr4-python3-runtime==4.13.2
Requires-Python: >=3.13
